Workbook

Sheet Infra Device (stock) 
A1: No. | B1: Item | C1: Type Device | D1: Stock | E1: Note | F1: sw
A2: 1 | B2: Ram 4Gb | C2: Ram | D2: =SUMIFS('Infra Device (transactions)'!F:F,'Infra Device (transactions)'!B:B,B2,'Infra Device (transactions)'!E:E,"In") - SUMIFS('Infra Device (transactions)'!F:F,'Infra Device (transactions)'!B:B,B2,'Infra Device (transactions)'!E:E,"Out") -> 1
A3: =A2+1 -> 2 | B3: Maken MK410 | C3: Cash Drawer | D3: =SUMIFS('Infra Device (transactions)'!F:F,'Infra Device (transactions)'!B:B,B3,'Infra Device (transactions)'!E:E,"In") - SUMIFS('Infra Device (transactions)'!F:F,'Infra Device (transactions)'!B:B,B3,'Infra Device (transactions)'!E:E,"Out") -> 7
A4: =A3+1 -> 3 | B4: Antech | C4: Cash Drawer | D4: =SUMIFS('Infra Device (transactions)'!F:F,'Infra Device (transactions)'!B:B,B4,'Infra Device (transactions)'!E:E,"In") - SUMIFS('Infra Device (transactions)'!F:F,'Infra Device (transactions)'!B:B,B4,'Infra Device (transactions)'!E:E,"Out") -> 2
A5: =A4+1 -> 4 | B5: Poscom | C5: Cash Drawer | D5: =SUMIFS('Infra Device (transactions)'!F:F,'Infra Device (transactions)'!B:B,B5,'Infra Device (transactions)'!E:E,"In") - SUMIFS('Infra Device (transactions)'!F:F,'Infra Device (transactions)'!B:B,B5,'Infra Device (transactions)'!E:E,"Out") -> 4
A6: =A5+1 -> 5 | B6: KA410 | C6: Cash Drawer | D6: =SUMIFS('Infra Device (transactions)'!F:F,'Infra Device (transactions)'!B:B,B6,'Infra Device (transactions)'!E:E,"In") - SUMIFS('Infra Device (transactions)'!F:F,'Infra Device (transactions)'!B:B,B6,'Infra Device (transactions)'!E:E,"Out") -> 1
A7: =A6+1 -> 6 | B7: Cash drawer of mall | C7: Cash Drawer | D7: =SUMIFS('Infra Device (transactions)'!F:F,'Infra Device (transactions)'!B:B,B7,'Infra Device (transactions)'!E:E,"In") - SUMIFS('Infra Device (transactions)'!F:F,'Infra Device (transactions)'!B:B,B7,'Infra Device (transactions)'!E:E,"Out") -> 2
A8: =A7+1 -> 7 | B8: Epson L850 | C8: Color Printer | D8: =SUMIFS('Infra Device (transactions)'!F:F,'Infra Device (transactions)'!B:B,B8,'Infra Device (transactions)'!E:E,"In") - SUMIFS('Infra Device (transactions)'!F:F,'Infra Device (transactions)'!B:B,B8,'Infra Device (transactions)'!E:E,"Out") -> 1
A9: =A8+1 -> 8 | B9: HP Laserjet P2055D | C9: A4 Printer | D9: =SUMIFS('Infra Device (transactions)'!F:F,'Infra Device (transactions)'!B:B,B9,'Infra Device (transactions)'!E:E,"In") - SUMIFS('Infra Device (transactions)'!F:F,'Infra Device (transactions)'!B:B,B9,'Infra Device (transactions)'!E:E,"Out") -> 1
A10: =A9+1 -> 9 | B10: Epson TM-U220A | C10: Bill Printer | D10: =SUMIFS('Infra Device (transactions)'!F:F,'Infra Device (transactions)'!B:B,B10,'Infra Device (transactions)'!E:E,"In") - SUMIFS('Infra Device (transactions)'!F:F,'Infra Device (transactions)'!B:B,B10,'Infra Device (transactions)'!E:E,"Out") -> 3
A11: =A10+1 -> 10 | B11: Canon L11121E | C11: A4 Printer | D11: =SUMIFS('Infra Device (transactions)'!F:F,'Infra Device (transactions)'!B:B,B11,'Infra Device (transactions)'!E:E,"In") - SUMIFS('Infra Device (transactions)'!F:F,'Infra Device (transactions)'!B:B,B11,'Infra Device (transactions)'!E:E,"Out") -> 1
A12: =A11+1 -> 11 | B12: Canon LBP 2900 | C12: A4 Printer | D12: =SUMIFS('Infra Device (transactions)'!F:F,'Infra Device (transactions)'!B:B,B12,'Infra Device (transactions)'!E:E,"In") - SUMIFS('Infra Device (transactions)'!F:F,'Infra Device (transactions)'!B:B,B12,'Infra Device (transactions)'!E:E,"Out") -> 7
A13: =A12+1 -> 12 | B13: HP Laserjet pro M15w | C13: A4 Printer | D13: =SUMIFS('Infra Device (transactions)'!F:F,'Infra Device (transactions)'!B:B,B13,'Infra Device (transactions)'!E:E,"In") - SUMIFS('Infra Device (transactions)'!F:F,'Infra Device (transactions)'!B:B,B13,'Infra Device (transactions)'!E:E,"Out") -> 2
A14: =A13+1 -> 13 | B14: HP Laserjet pro M12w | C14: A4 Printer | D14: =SUMIFS('Infra Device (transactions)'!F:F,'Infra Device (transactions)'!B:B,B14,'Infra Device (transactions)'!E:E,"In") - SUMIFS('Infra Device (transactions)'!F:F,'Infra Device (transactions)'!B:B,B14,'Infra Device (transactions)'!E:E,"Out") -> 2
A15: =A14+1 -> 14 | B15: HP Pavilion 550-029I | C15: Desktop | D15: =SUMIFS('Infra Device (transactions)'!F:F,'Infra Device (transactions)'!B:B,B15,'Infra Device (transactions)'!E:E,"In") - SUMIFS('Infra Device (transactions)'!F:F,'Infra Device (transactions)'!B:B,B15,'Infra Device (transactions)'!E:E,"Out") -> 2 | E15: Location: Pantry room
A16: =A15+1 -> 15 | B16: PC-none use | C16: Desktop | D16: =SUMIFS('Infra Device (transactions)'!F:F,'Infra Device (transactions)'!B:B,B16,'Infra Device (transactions)'!E:E,"In") - SUMIFS('Infra Device (transactions)'!F:F,'Infra Device (transactions)'!B:B,B16,'Infra Device (transactions)'!E:E,"Out") -> 4 | E16: Location: Pantry room
A17: =A16+1 -> 16 | B17: HDD 500Gb | C17: hard disk drive | D17: =SUMIFS('Infra Device (transactions)'!F:F,'Infra Device (transactions)'!B:B,B17,'Infra Device (transactions)'!E:E,"In") - SUMIFS('Infra Device (transactions)'!F:F,'Infra Device (transactions)'!B:B,B17,'Infra Device (transactions)'!E:E,"Out") -> 7
A18: =A17+1 -> 17 | B18: HP ProDesk 400 G3 DM | C18: Mini Pc | D18: =SUMIFS('Infra Device (transactions)'!F:F,'Infra Device (transactions)'!B:B,B18,'Infra Device (transactions)'!E:E,"In") - SUMIFS('Infra Device (transactions)'!F:F,'Infra Device (transactions)'!B:B,B18,'Infra Device (transactions)'!E:E,"Out") -> 7
A19: =A18+1 -> 18 | B19: HP 280 G3 MT | C19: Desktop | D19: =SUMIFS('Infra Device (transactions)'!F:F,'Infra Device (transactions)'!B:B,B19,'Infra Device (transactions)'!E:E,"In") - SUMIFS('Infra Device (transactions)'!F:F,'Infra Device (transactions)'!B:B,B19,'Infra Device (transactions)'!E:E,"Out") -> 2
A20: =A19+1 -> 19 | B20: HP 190V | C20: Monitor | D20: =SUMIFS('Infra Device (transactions)'!F:F,'Infra Device (transactions)'!B:B,B20,'Infra Device (transactions)'!E:E,"In") - SUMIFS('Infra Device (transactions)'!F:F,'Infra Device (transactions)'!B:B,B20,'Infra Device (transactions)'!E:E,"Out") -> 10
A21: =A20+1 -> 20 | B21: HP 194V | C21: Monitor | D21: =SUMIFS('Infra Device (transactions)'!F:F,'Infra Device (transactions)'!B:B,B21,'Infra Device (transactions)'!E:E,"In") - SUMIFS('Infra Device (transactions)'!F:F,'Infra Device (transactions)'!B:B,B21,'Infra Device (transactions)'!E:E,"Out") -> 3
A22: =A21+1 -> 21 | B22: AOC 1619Sw | C22: Monitor | D22: =SUMIFS('Infra Device (transactions)'!F:F,'Infra Device (transactions)'!B:B,B22,'Infra Device (transactions)'!E:E,"In") - SUMIFS('Infra Device (transactions)'!F:F,'Infra Device (transactions)'!B:B,B22,'Infra Device (transactions)'!E:E,"Out") -> 1
A23: =A22+1 -> 22 | B23: AOC 931Swl | C23: Monitor | D23: =SUMIFS('Infra Device (transactions)'!F:F,'Infra Device (transactions)'!B:B,B23,'Infra Device (transactions)'!E:E,"In") - SUMIFS('Infra Device (transactions)'!F:F,'Infra Device (transactions)'!B:B,B23,'Infra Device (transactions)'!E:E,"Out") -> 2
A24: =A23+1 -> 23 | B24: Samsung B1930N | C24: Monitor | D24: =SUMIFS('Infra Device (transactions)'!F:F,'Infra Device (transactions)'!B:B,B24,'Infra Device (transactions)'!E:E,"In") - SUMIFS('Infra Device (transactions)'!F:F,'Infra Device (transactions)'!B:B,B24,'Infra Device (transactions)'!E:E,"Out") -> 1
A25: =A24+1 -> 24 | B25: Acer P196HQL | C25: Monitor | D25: =SUMIFS('Infra Device (transactions)'!F:F,'Infra Device (transactions)'!B:B,B25,'Infra Device (transactions)'!E:E,"In") - SUMIFS('Infra Device (transactions)'!F:F,'Infra Device (transactions)'!B:B,B25,'Infra Device (transactions)'!E:E,"Out") -> 1
A26: =A25+1 -> 25 | B26: D-LINK DIR-619L | C26: Router | D26: =SUMIFS('Infra Device (transactions)'!F:F,'Infra Device (transactions)'!B:B,B26,'Infra Device (transactions)'!E:E,"In") - SUMIFS('Infra Device (transactions)'!F:F,'Infra Device (transactions)'!B:B,B26,'Infra Device (transactions)'!E:E,"Out") -> 0
A27: =A26+1 -> 26 | B27: HDMI to HDMI (3M) | C27: HDMI Cable | D27: =SUMIFS('Infra Device (transactions)'!F:F,'Infra Device (transactions)'!B:B,B27,'Infra Device (transactions)'!E:E,"In") - SUMIFS('Infra Device (transactions)'!F:F,'Infra Device (transactions)'!B:B,B27,'Infra Device (transactions)'!E:E,"Out") -> 2
A28: =A27+1 -> 27 | B28: Lion (3 Port) | C28: Power socket | D28: =SUMIFS('Infra Device (transactions)'!F:F,'Infra Device (transactions)'!B:B,B28,'Infra Device (transactions)'!E:E,"In") - SUMIFS('Infra Device (transactions)'!F:F,'Infra Device (transactions)'!B:B,B28,'Infra Device (transactions)'!E:E,"Out") -> 1
... A147: =A146+1 -> 146 | B147: Dell E2216HV | C147: Monitor | D147: =SUMIFS('Infra Device (transactions)'!F:F,'Infra Device (transactions)'!B:B,B147,'Infra Device (transactions)'!E:E,"In") - SUMIFS('Infra Device (transactions)'!F:F,'Infra Device (transactions)'!B:B,B147,'Infra Device (transactions)'!E:E,"Out") -> 1
A148: 147 | B148: TP link tl sf1008d | C148: Switch | D148: =SUMIFS('Infra Device (transactions)'!F:F,'Infra Device (transactions)'!B:B,B148,'Infra Device (transactions)'!E:E,"In") - SUMIFS('Infra Device (transactions)'!F:F,'Infra Device (transactions)'!B:B,B148,'Infra Device (transactions)'!E:E,"Out") -> 1
A149: =A148+1 -> 148 | B149: USB Wifi TP-Link AC1300 | C149: USB Wifi TP-Link | D149: =SUMIFS('Infra Device (transactions)'!F:F,'Infra Device (transactions)'!B:B,B149,'Infra Device (transactions)'!E:E,"In") - SUMIFS('Infra Device (transactions)'!F:F,'Infra Device (transactions)'!B:B,B149,'Infra Device (transactions)'!E:E,"Out") -> 1
A150: =A149+1 -> 149 | B150: KPOS-VFD-220U | C150: Pole Display | D150: =SUMIFS('Infra Device (transactions)'!F:F,'Infra Device (transactions)'!B:B,B150,'Infra Device (transactions)'!E:E,"In") - SUMIFS('Infra Device (transactions)'!F:F,'Infra Device (transactions)'!B:B,B150,'Infra Device (transactions)'!E:E,"Out") -> 1
A151: =A150+1 -> 150 | B151: Wifi UBIQUITI UniFi | C151: Access Point | D151: =SUMIFS('Infra Device (transactions)'!F:F,'Infra Device (transactions)'!B:B,B151,'Infra Device (transactions)'!E:E,"In") - SUMIFS('Infra Device (transactions)'!F:F,'Infra Device (transactions)'!B:B,B151,'Infra Device (transactions)'!E:E,"Out") -> 16
A152: =A151+1 -> 151 | B152: Ugreen Silent MU006 Wireless Mouse | C152: mouse | D152: =SUMIFS('Infra Device (transactions)'!F:F,'Infra Device (transactions)'!B:B,B152,'Infra Device (transactions)'!E:E,"In") - SUMIFS('Infra Device (transactions)'!F:F,'Infra Device (transactions)'!B:B,B152,'Infra Device (transactions)'!E:E,"Out") -> 0
A153: =A152+1 -> 152 | B153: Ipad Air 13-inch(M3) | C153: Tablet | D153: =SUMIFS('Infra Device (transactions)'!F:F,'Infra Device (transactions)'!B:B,B153,'Infra Device (transactions)'!E:E,"In") - SUMIFS('Infra Device (transactions)'!F:F,'Infra Device (transactions)'!B:B,B153,'Infra Device (transactions)'!E:E,"Out") -> 0 | E153: only for VN Asics
A154: =A153+1 -> 153 | B154: RUIJIE REEYE RG-EW1200G Pro | C154: Access Point | D154: =SUMIFS('Infra Device (transactions)'!F:F,'Infra Device (transactions)'!B:B,B154,'Infra Device (transactions)'!E:E,"In") - SUMIFS('Infra Device (transactions)'!F:F,'Infra Device (transactions)'!B:B,B154,'Infra Device (transactions)'!E:E,"Out") -> 0
A155: =A154+1 -> 154 | B155: Desktop HP PRO MINI 400 G9 | C155: Mini PC | D155: =SUMIFS('Infra Device (transactions)'!F:F,'Infra Device (transactions)'!B:B,B155,'Infra Device (transactions)'!E:E,"In") - SUMIFS('Infra Device (transactions)'!F:F,'Infra Device (transactions)'!B:B,B155,'Infra Device (transactions)'!E:E,"Out") -> 1
A156: =A155+1 -> 155 | B156: aruba ap 535 jz336a | C156: Access Point | D156: =SUMIFS('Infra Device (transactions)'!F:F,'Infra Device (transactions)'!B:B,B156,'Infra Device (transactions)'!E:E,"In") - SUMIFS('Infra Device (transactions)'!F:F,'Infra Device (transactions)'!B:B,B156,'Infra Device (transactions)'!E:E,"Out") -> 7
A157: =A156+1 -> 156 | B157: SATO CL4NX Plus | C157: Printer | D157: =SUMIFS('Infra Device (transactions)'!F:F,'Infra Device (transactions)'!B:B,B157,'Infra Device (transactions)'!E:E,"In") - SUMIFS('Infra Device (transactions)'!F:F,'Infra Device (transactions)'!B:B,B157,'Infra Device (transactions)'!E:E,"Out") -> 2
A158: =A157+1 -> 157 | B158: HP V22 | C158: monitor | D158: =SUMIFS('Infra Device (transactions)'!F:F,'Infra Device (transactions)'!B:B,B158,'Infra Device (transactions)'!E:E,"In") - SUMIFS('Infra Device (transactions)'!F:F,'Infra Device (transactions)'!B:B,B158,'Infra Device (transactions)'!E:E,"Out") -> 8
A159: =A158+1 -> 158 | B159: HPE Aruba 2930F | C159: Switch | D159: =SUMIFS('Infra Device (transactions)'!F:F,'Infra Device (transactions)'!B:B,B159,'Infra Device (transactions)'!E:E,"In") - SUMIFS('Infra Device (transactions)'!F:F,'Infra Device (transactions)'!B:B,B159,'Infra Device (transactions)'!E:E,"Out") -> 2
A160: =A159+1 -> 159 | B160: Samsung Tab A8 | C160: tablet | D160: =SUMIFS('Infra Device (transactions)'!F:F,'Infra Device (transactions)'!B:B,B160,'Infra Device (transactions)'!E:E,"In") - SUMIFS('Infra Device (transactions)'!F:F,'Infra Device (transactions)'!B:B,B160,'Infra Device (transactions)'!E:E,"Out") -> 2
A161: =A160+1 -> 160 | B161: Canon MF445dw | C161: A4 printer | D161: =SUMIFS('Infra Device (transactions)'!F:F,'Infra Device (transactions)'!B:B,B161,'Infra Device (transactions)'!E:E,"In") - SUMIFS('Infra Device (transactions)'!F:F,'Infra Device (transactions)'!B:B,B161,'Infra Device (transactions)'!E:E,"Out") -> 1
A162: =A161+1 -> 161 | B162: Zebra DS2208-SR (wired) | C162: Barcode Scanner | D162: =SUMIFS('Infra Device (transactions)'!F:F,'Infra Device (transactions)'!B:B,B162,'Infra Device (transactions)'!E:E,"In") - SUMIFS('Infra Device (transactions)'!F:F,'Infra Device (transactions)'!B:B,B162,'Infra Device (transactions)'!E:E,"Out") -> 5
A163: =A162+1 -> 162 | B163: Zebra DS2208-SR (wireless) | C163: Barcode Scanner | D163: =SUMIFS('Infra Device (transactions)'!F:F,'Infra Device (transactions)'!B:B,B163,'Infra Device (transactions)'!E:E,"In") - SUMIFS('Infra Device (transactions)'!F:F,'Infra Device (transactions)'!B:B,B163,'Infra Device (transactions)'!E:E,"Out") -> 3
A164: =A163+1 -> 163 | B164: Zebra DS2208-SR Dock | C164: Dock | D164: =SUMIFS('Infra Device (transactions)'!F:F,'Infra Device (transactions)'!B:B,B164,'Infra Device (transactions)'!E:E,"In") - SUMIFS('Infra Device (transactions)'!F:F,'Infra Device (transactions)'!B:B,B164,'Infra Device (transactions)'!E:E,"Out") -> 3
A165: =A164+1 -> 164 | B165: Saramonic Air 01 | C165: Micro thu âm | D165: =SUMIFS('Infra Device (transactions)'!F:F,'Infra Device (transactions)'!B:B,B165,'Infra Device (transactions)'!E:E,"In") - SUMIFS('Infra Device (transactions)'!F:F,'Infra Device (transactions)'!B:B,B165,'Infra Device (transactions)'!E:E,"Out") -> 0
... A167: =A166+1 -> 166 | B167: Samsung Tab S10 FE | C167: tablet | D167: =SUMIFS('Infra Device (transactions)'!F:F,'Infra Device (transactions)'!B:B,B167,'Infra Device (transactions)'!E:E,"In") - SUMIFS('Infra Device (transactions)'!F:F,'Infra Device (transactions)'!B:B,B167,'Infra Device (transactions)'!E:E,"Out") -> 0

Sheet Infra Device (transactions)
A1: No. | B1: Item | C1: Description | D1: Date | E1: Transaction Type | F1: Quantity | G1: Unit | H1: Assigned | I1: Assign history | J1: Status | K1: S/N | L1: Remark
A2: 1 | B2: Ram 4Gb | D2: 16/02/2024 | E2: in | F2: 4 | G2: pcs | H2: Stock IT
A3: 2 | B3: Ram 4Gb | C3: upgrade linh.lengocmy's laptop | D3: 16/02/2024 | E3: out | F3: 1 | G3: pcs | H3: linh.lengocmy | L3: Broken: can't fix None-use: Don't use anymore and don't the status of device
A4: 3 | B4: Maken MK410 | D4: 22/02/2024 | E4: In | F4: 8 | G4: pcs | H4: Stock IT | K4: MK410221102420 MK410220300197 MK410211201000 MK410211201512 MK410220300423 MK410221102371 MK410221102347 MK410220300326
A5: 4 | B5: Antech | D5: 22/02/2024 | E5: In | F5: 1 | G5: pcs | H5: Stock IT | K5: DGAV141220180773 B5AT100009
A6: 5 | B6: Poscom | D6: 22/02/2024 | E6: In | F6: 2 | G6: pcs | H6: Stock IT | K6: 2020092533
A7: 6 | B7: KA410 | D7: 22/02/2024 | E7: In | F7: 1 | G7: pcs | H7: Stock IT | K7: 20230526081
A8: 7 | B8: Cash drawer of mall | C8: Quỳnh AM đóng nhầm cash drawer của smart city | D8: 22/02/2024 | E8: In | F8: 1 | G8: pcs | H8: Stock IT | K8: 200414009618
A9: 8 | B9: Epson L850 | C9: Broken -Mr.Dat confirmed can't fix because don't have replacement components | D9: 22/02/2024 | E9: In | F9: 1 | G9: pcs | H9: Stock IT | J9: Broken | K9: UTUY000488
A10: 9 | B10: HP Laserjet P2055D | C10: Broken -Mr.Dat confirmed can't fix because don't have replacement components | D10: 22/02/2024 | E10: In | F10: 1 | G10: pcs | H10: Stock IT | J10: Broken | K10: CNCJY00421
A11: 10 | B11: Epson TM-U220A | C11: Lose power supply, usb cable - Indo not use this model anymore (Mr.Dat confirmed) | D11: 22/02/2024 | E11: In | F11: 3 | G11: pcs | H11: Stock IT | J11: Broken | K11: L98F275060 L97F002416 L9CF300124
A12: 11 | B12: Canon L11121E | C12: Old | D12: 22/02/2024 | E12: In | F12: 1 | G12: pcs | H12: Stock IT | I12: VN14 | K12: NMYA744682
A13: 12 | B13: Canon LBP 2900 | C13: New, lô hàng satatech | D13: 22/02/2024 | E13: In | F13: 1 | G13: pcs | H13: Stock IT | K13: NMYA783808
A14: 13 | B14: HP Laserjet pro M15w | C14: Old | D14: 22/02/2024 | E14: In | F14: 1 | G14: pcs | H14: Stock IT | I14: VF02 | K14: VNC3K04690
A15: 14 | B15: HP Laserjet pro M15w | C15: Old | D15: 22/02/2024 | E15: In | F15: 1 | G15: pcs | H15: Stock IT | I15: PO02 | K15: VNC3K04070
A16: 15 | B16: HP Laserjet pro M15w | C16: Old | D16: 22/02/2024 | E16: In | F16: 1 | G16: pcs | H16: Stock IT | I16: VC01 | K16: VNC3K05078
A17: 16 | B17: HP Laserjet pro M12w | C17: Old | D17: 22/02/2024 | E17: In | F17: 1 | G17: pcs | H17: Stock IT | I17: ZV09-12 | K17: VNCW613481
A18: 17 | B18: Antech | C18: Old | D18: 22/02/2024 | E18: In | F18: 1 | G18: pcs | H18: Stock IT | I18: VF02 | K18: DGAV141220180609
A19: 18 | B19: HP Pavilion 550-029I | C19: Old | D19: 22/02/2024 | E19: In | F19: 1 | G19: pcs | H19: Location: Pantry room | I19: Un-known | J19: None-use | K19: 4CE5360DVB
A20: 19 | B20: PC-none use | C20: Don't know information - don't have any info on the case | D20: 22/02/2024 | E20: In | F20: 4 | G20: pcs | H20: Location: Pantry room | I20: Un-known | J20: None-use
A21: 20 | B21: HDD 500Gb | C21: Old | D21: 22/02/2024 | E21: In | F21: 1 | G21: pcs | H21: Stock IT | I21: PO01-Admin | J21: None-use | K21: W62LE31F
A22: 21 | B22: HDD 500Gb | C22: Old | D22: 22/02/2024 | E22: In | F22: 1 | G22: pcs | H22: Stock IT | I22: PO01-Pos2 | J22: None-use | K22: W62KW2KT
A23: 22 | B23: HDD 500Gb | C23: Old | D23: 22/02/2024 | E23: In | F23: 1 | G23: pcs | H23: Stock IT | I23: PO02-Pos1 | J23: None-use | K23: W62L7N1A
A24: 23 | B24: HDD 500Gb | C24: Old | D24: 22/02/2024 | E24: In | F24: 1 | G24: pcs | H24: Stock IT | I24: PO01-Server | J24: None-use | K24: W62LFH4H
A25: 24 | B25: HDD 500Gb | C25: Old | D25: 22/02/2024 | E25: In | F25: 1 | G25: pcs | H25: Stock IT | I25: PO01-POS | J25: None-use | K25: W62KWFS9
A26: 25 | B26: HDD 500Gb | C26: Old | D26: 22/02/2024 | E26: In | F26: 1 | G26: pcs | H26: Stock IT | I26: PO02-Pos2 | J26: None-use | K26: W62LFM8W
A27: 26 | B27: HDD 500Gb | C27: Old | D27: 22/02/2024 | E27: In | F27: 1 | G27: pcs | H27: Stock IT | I27: PO02-Server | J27: None-use | K27: W62L7N7S
A28: 27 | B28: HP ProDesk 400 G3 DM | C28: Bazzar | D28: 26/02/2024 | E28: In | F28: 1 | G28: pcs | H28: ZK05-ZW05-ZV05 | K28: 8CG7127F7Q
A29: 28 | B29: HP ProDesk 400 G3 DM | C29: Bazzar | D29: 26/02/2024 | E29: In | F29: 1 | G29: pcs | H29: ZV01-H103-H104 | K29: 8CG8105MSK
A30: 29 | B30: HP ProDesk 400 G3 DM | C30: Bazzar | D30: 26/02/2024 | E30: In | F30: 1 | G30: pcs | H30: H101-H102 | K30: 8CG75234Q2
A31: 30 | B31: HP 280 G3 MT | C31: none-info | D31: 26/02/2024 | E31: In | F31: 1 | G31: pcs | H31: None-info | K31: 4CE7385WT0
A32: 31 | B32: HP 190V | D32: 26/02/2024 | E32: In | F32: 1 | G32: pcs | H32: ZK05-ZW05-ZV05-ZV01-H103-H104-H101-H102 | K32: 1CR8420G66
A33: 32 | B33: HP 190V | D33: 26/02/2024 | E33: In | F33: 1 | G33: pcs | H33: VN17 | K33: 1CR82307D4
A34: 33 | B34: HP 190V | D34: 26/02/2024 | E34: In | F34: 1 | G34: pcs | H34: VF02 | K34: 1CR84126GF
A35: 34 | B35: HP 194V | C35: IT-BACKUP | D35: 26/02/2024 | E35: In | F35: 1 | G35: pcs | K35: 3CQ6361YDZ
A36: 35 | B36: HP 190V | C36: Mất đế | D36: 26/02/2024 | E36: In | F36: 1 | G36: pcs | H36: PO01 | K36: 1CR82307CY
A37: 36 | B37: HP 190V | C37: Mất đế | D37: 26/02/2024 | E37: In | F37: 1 | G37: pcs | H37: PO01 | K37: 1CR82307CJ
A38: 37 | B38: AOC 1619Sw | C38: Old | D38: 26/02/2024 | E38: In | F38: 1 | G38: pcs | K38: BMNB3JA000570
A39: 38 | B39: AOC 931Swl | C39: Old | D39: 26/02/2024 | E39: In | F39: 1 | G39: pcs | K39: CLCBCHA033328
A40: 39 | B40: Samsung B1930N | C40: Old | D40: 26/02/2024 | E40: In | F40: 1 | G40: pcs | K40: 1458HYTZ912979F
A41: 40 | B41: Acer P196HQL | C41: Old | D41: 26/02/2024 | E41: In | F41: 1 | G41: pcs | K41: MMLNNSS002238003D34301
A42: 41 | B42: AOC 931Swl | C42: Old | D42: 26/02/2024 | E42: In | F42: 1 | G42: pcs | K42: CLCBAHA018980
A43: 42 | B43: D-LINK DIR-619L | D43: 26/02/2024 | E43: In | F43: 1 | G43: pcs | K43: RZPK2G2000820
A44: 43 | B44: Lion (3 Port) | D44: 26/02/2024 | E44: In | F44: 1 | G44: pcs
A45: 44 | B45: Power socket | D45: 26/02/2024 | E45: In | F45: 2 | G45: pcs
A46: 45 | B46: Cable extend usb | C46: IT Tool | D46: 26/02/2024 | E46: In | F46: 1 | G46: pcs
A47: 46 | B47: Comscope Cat5e | D47: 26/02/2024 | E47: In | F47: 2 | G47: Box
A48: 47 | B48: Keyboard | D48: 26/02/2024 | E48: In | F48: 17 | G48: Pcs
A49: 48 | B49: Mouse | D49: 26/02/2024 | E49: In | F49: 16 | G49: Pcs
A50: 49 | B50: Aruba APIN0303 | C50: FPT tặng khi kéo line internet dành cho mạng wifi guest | D50: 26/02/2024 | E50: In | F50: 1 | G50: Pcs | K50: CNNZK9T2C8
A51: 50 | B51: Ruckus R720 | C51: Set up cho office cũ | D51: 26/02/2024 | E51: In | F51: 1 | G51: Pcs | K51: 312172007180
A52: 51 | B52: Ruckus R720 | C52: Set up cho office cũ | D52: 26/02/2024 | E52: In | F52: 1 | G52: Pcs | K52: 361803002766
A53: 52 | B53: Avaya | D53: 26/02/2024 | E53: In | F53: 3 | G53: Pcs | K53: 19WZ29300DJW 19WZ29300DHK 19WZ29300D37
A54: 53 | B54: HDMI to HDMI (3M) | C54: IT Tool | D54: 26/02/2024 | E54: In | F54: 1 | G54: Pcs
A55: 54 | B55: TPink TL-WN725N | C55: IT Tool | D55: 26/02/2024 | E55: In | F55: 1 | G55: Pcs | K55: 222B4M9005853
A56: 55 | B56: Mercusys | C56: IT Tool | D56: 26/02/2024 | E56: In | F56: 1 | G56: Pcs | K56: 22253D9009592
A57: 56 | B57: Mercusys | C57: IT Tool | D57: 26/02/2024 | E57: In | F57: 1 | G57: Pcs | K57: 22253D8008268
A58: 57 | B58: Mercusys | C58: IT Tool | D58: 26/02/2024 | E58: In | F58: 1 | G58: Pcs | K58: 22253D9009871
A59: 58 | B59: Ugreen 4 port | C59: IT Tool | D59: 26/02/2024 | E59: In | F59: 1 | G59: Pcs | K59: SN2100201238804
A60: 59 | B60: VGA to HDMI | C60: IT Tool | D60: 26/02/2024 | E60: In | F60: 1 | G60: Pcs
A61: 60 | B61: HDMI to HDMI (2M) | C61: IT Tool | D61: 26/02/2024 | E61: In | F61: 1 | G61: Pcs
A62: 61 | B62: HDMI to HDMI (1M) - Baseus | C62: IT Tool | D62: 26/02/2024 | E62: In | F62: 1 | G62: Pcs
A63: 62 | B63: Lexar-32Gb | C63: IT Tool | D63: 26/02/2024 | E63: In | F63: 3 | G63: Pcs
A64: 63 | B64: Mercusys | C64: IT Tool | D64: 26/02/2024 | E64: In | F64: 1 | G64: Pcs | K64: 22172W5002268
A65: 64 | B65: Usb to Lan - Orico | C65: IT Tool | D65: 26/02/2024 | E65: In | F65: 1 | G65: Pcs
A66: 65 | B66: Hub Usb Orico 4 Port | C66: IT Tool | D66: 26/02/2024 | E66: In | F66: 1 | G66: Pcs
A67: 66 | B67: HDMI to HDMI - Unitek | C67: IT Tool | D67: 26/02/2024 | E67: In | F67: 1 | G67: Pcs
A68: 67 | B68: Usb to Lan - Ugreen | C68: IT Tool | D68: 26/02/2024 | E68: In | F68: 1 | G68: Pcs
A69: 68 | B69: Display port to Display Port | C69: IT Tool | D69: 26/02/2024 | E69: In | F69: 1 | G69: Pcs
A70: 69 | B70: HDMI to HDMI - Unitek | C70: IT Tool | D70: 26/02/2024 | E70: In | F70: 1 | G70: Pcs
A71: 70 | B71: Dlink - DSL 2640B | C71: IT Tool | D71: 26/02/2024 | E71: In | F71: 1 | G71: Pcs
A72: 71 | B72: Usb to Lan - Baseus | C72: IT Tool | D72: 26/02/2024 | E72: In | F72: 1 | G72: Pcs
A73: 72 | B73: Hub Usb Unitek - 4 Port | C73: IT Tool | D73: 26/02/2024 | E73: In | F73: 4 | G73: Pcs
A74: 73 | B74: Unitek - HDMI to VGA | C74: IT Tool | D74: 26/02/2024 | E74: In | F74: 1 | G74: Pcs
A75: 74 | B75: Epson Usb wifi | C75: IT Tool | D75: 27/02/2024 | E75: In | F75: 1 | G75: Pcs
A76: 75 | B76: Usb To Lan - Asus | C76: IT Tool | D76: 27/02/2024 | E76: In | F76: 1 | G76: Pcs
A77: 76 | B77: Epson TM-82II | C77: Use for ZV08 | D77: 27/02/2024 | E77: In | F77: 1 | G77: Pcs | I77: ZV08 | K77: TCEY002724
A78: 77 | B78: Epson TM-82II | C78: IT Backup | D78: 27/02/2024 | E78: In | F78: 1 | G78: Pcs | K78: TCEY004688
A79: 78 | B79: Epson TM-82II | C79: IT Backup | D79: 27/02/2024 | E79: In | F79: 1 | G79: Pcs | I79: VF02 | K79: TCCY011123
A80: 79 | B80: Epson TM-82II | C80: IT Backup | D80: 27/02/2024 | E80: In | F80: 1 | G80: Pcs | I80: PO02 | K80: TCCY011122
A81: 80 | B81: Laptop Thinkpad X280 | C81: IT Backup | D81: 27/02/2024 | E81: In | F81: 1 | G81: Pcs | I81: Ko Ni (Hr) | K81: PC0VT5RC
A82: 81 | B82: Laptop Dell Latitude 3520 | C82: IT Backup | D82: 27/02/2024 | E82: In | F82: 1 | G82: Pcs | I82: thy.nguyenhoanganh | K82: 5R4JGL3
A83: 82 | B83: Laptop Dell Latitude 3520 | C83: IT Backup | D83: 27/02/2024 | E83: In | F83: 1 | G83: Pcs | I83: khang.leminh | K83: DP8VKG3
A84: 83 | B84: Laptop Dell Latitude 3520 | C84: IT Backup | D84: 27/02/2024 | E84: In | F84: 1 | G84: Pcs | I84: khoa.trandanganh (Coe) | K84: 6S4JGL3
A85: 84 | B85: Laptop Dell Latitude 3520 | C85: Laptop trước là của Phan Bảo Hoàng làm rớt bể không xài được nữa, không có nguồn, mất 1 ram. Anh Đạt nói lúc đó chưa có quy trình bảo hành hay đền gì hết chỉ cấp máy mới cho Hoang nên cần phải check lại với team HR. | D85: 27/02/2024 | E85: In | F85: 1 | G85: Pcs | J85: Broken | K85: 4R4JGL3
A86: 85 | B86: Laptop Dell Latitude 5430 | C86: IT Backup | D86: 27/02/2024 | E86: In | F86: 1 | G86: Pcs | I86: quynh.nguyennhu (Bata) | K86: 4084RV3
A87: 86 | B87: Laptop Dell Latitude 5430 | C87: Maintanance | D87: 27/02/2024 | E87: In | F87: 1 | G87: Pcs | I87: chi.tranvukim | K87: F083SQ3
A88: 87 | B88: Laptop HP 14s-cf2xxx | C88: IT Backup | D88: 27/02/2024 | E88: In | F88: 1 | G88: Pcs | I88: VI02 | K88: 5CG11088PT
A89: 88 | B89: HP 4-1011TU | C89: Máy cũ cấp cho anh Thắng COE từ rất lâu | D89: 27/02/2024 | E89: In | F89: 1 | G89: Pcs | I89: thang.nguyenquyet | J89: Broken | K89: CND218PWRZ
A90: 89 | B90: HP Elitebook 840 G4 | C90: không biết mãy này trước của ai | D90: 27/02/2024 | E90: In | F90: 1 | G90: Pcs | I90: Un-known | J90: Broken | K90: CG7325LVQ
A91: 90 | B91: HP Probook 440 G2 | D91: 27/02/2024 | E91: In | F91: 1 | G91: Pcs | I91: VI04-VN19
A92: 91 | B92: Dell Vostro 14-5480 | D92: 27/02/2024 | E92: In | F92: 1 | G92: Pcs | I92: Un-known | J92: Broken
A93: 92 | B93: Laptop Dell Latitude 5430 | C93: Maintanance | D93: 27/02/2024 | E93: In | F93: 1 | G93: Pcs | H93: minh.lengocbao | I93: giang.nguyenthiquynh | K93: GB23SQ3
A94: 93 | B94: Laptop Dell Latitude 3520 | C94: Resigned-tram.phanthibao (MKT | D94: 29/02/2024 | E94: in | F94: 1 | G94: pcs | I94: tram.phanthibao | K94: 1P8VKG3
A95: 94 | B95: Brother Label | D95: 29/02/2024 | E95: in | F95: 5 | G95: pcs
A96: 95 | B96: Laptop Dell Latitude 3520 | C96: IT backup-Lô hàng Cambodia | D96: 29/02/2024 | E96: in | F96: 1 | G96: pcs
A97: 96 | B97: Laptop Dell Latitude 3520 | D97: 29/02/2024 | E97: in | F97: 1 | G97: pcs | I97: hieu.nguyenvutrung | K97: 6XSSKS3
A98: 97 | B98: Ổ SSD 256 Gb | C98: Ổ cứng cũ của anh Sơn PD | D98: 29/02/2024 | E98: in | F98: 1 | G98: pcs | J98: still use | K98: 2109CY452920
A99: 98 | B99: Ổ HDD | C99: Bad | D99: 29/02/2024 | E99: in | F99: 1 | G99: pcs | J99: Broken
A100: 99 | B100: Ổ HDD | C100: POS PO01 - old | D100: 29/02/2024 | E100: in | F100: 1 | G100: pcs | I100: PO01 | J100: still use
...

Sheet Mini PC status
A1: Asset Code | B1: Model | C1: Vendor | D1: Hardware | E1: Computer Name | F1: Serial number | G1: MAC Address LAN | H1: MAC Address WiFi | I1: OS | J1: Note
A2: VC01 | B2: ProDesk 400 G3 Mini | C2: HP | D2: CPUi5-7500T 2.7 GHz/RAM 8GB DDR4 2400 MHz(4x2) /SDD500 GB (VN17/SN:S7BWNJ0W745993K) | E2: x | F2: 8CG8105MSQ | G2: 10-E7-C6-08-74-27 | H2: 7A-5D-42-60-77-95 | I2: W10 | J2: K301-ADMIN
A3: VC03-Admin | B3: ProDesk 400 G3 Mini | C3: HP | D3: CPUi5-7500T 2.7 GHz/RAM 8GB DDR4 2400 MHz(4x2) /HDD500 GB | E3: x | F3: 8CG75206VW | H3: C8-09-A8-BC-32-11 | I3: W10 | J3: hư nguồn, usb
A4: P001-Admin | B4: ProDesk 400 G3 Mini | C4: HP | D4: CPUi5-7500T 2.7 GHz/RAM 12GB DDR4 2400 MHz(4x1, 8x1) /HDD500 GB | E4: x | F4: 8CGG75234QP | H4: C8-09-A8-DC-1F-B3 | I4: W10 | J4: lổi bios ko nhận usb, 2 cổng usb trước hư
A5: P002-Admin | B5: ProDesk 400 G3 Mini | C5: HP | D5: CPUi5-7500T 2.7 GHz/RAM 8GB DDR4 2400 MHz(4x2) /SSD500 GB(SN:S6P6NL0TC39331V) | E5: x | F5: 8CG8105N1T | G5: 10-E7-C6-08-72-F0 | H5: E0-9D-31-D3-FF-6D | I5: W10 | J5: VN15-ADMIN
A6: VF02-ADMIN | B6: ProDesk 400 G3 Mini | C6: HP | D6: CPUi5-7500T 2.7 GHz/RAM 8GB DDR4 2400 MHz(4x2) /HDD500 GB | E6: x | F6: 8CG8052W2H | G6: 10-E7-C6-01-40-83 | H6: 4E-FB-C8-A6-0B-49 | I6: w10 | J6: hư 1 cổng usb trước
A7: VN20-Admin | B7: Optiplex 3090 | C7: Dell | J7: Đang kím nguồn
A8: VN17 | J8: đang đóng store
A9: Bazzar
A10: Bazzar

Sheet Sheet1
A1: VN05 | B1: Converse Crescent mall | C1: Trần Phạm Minh Ngọc | D1: Supervisor | E1: 704447276 | F1: VO LAM MINH DAT
A2: VN07 | B2: Converse Nguyen Trai D1 | C2: Nguyễn Ngọc Thiện | D2: Supervisor | E2: 379932155 | F2: VO LAM MINH DAT
A3: VN16 | B3: Converse Ba Thang Hai D10 | C3: Nguyễn Thanh Danh | D3: Supervisor | E3: 931771497 | F3: VO LAM MINH DAT
A4: VN09 | B4: Converse Aeon Canary | C4: Đinh Hồng Hạnh | D4: Supervisor | E4: 965314912 | F4: DUONG QUANG MINH TUAN
A5: VN10 | B5: Converse Aeon Binh Tan | C5: Trần Thị Kim Huệ | D5: Supervisor | E5: 904187104 | F5: DUONG QUANG MINH TUAN
A6: VN08 | B6: Converse Hai Ba Trung D3 | C6: Huỳnh Văn Thiện | D6: Supervisor | E6: 328955231 | F6: VO LAM MINH DAT
A7: VN19 | B7: Converse Gold Coast | C7: Dương Anh Quốc | D7: Supervisor | E7: 898460922 | F7: VO LAM MINH DAT
A8: VN27 | B8: Converse CFS Quang Trung | C8: Nguyễn Văn Huy | D8: Store Manager | E8: 383438670 | F8: DAO DUC HUY
A9: VI03 | B9: Smiggle Estella | C9: Nguyễn Kim Phương Uyên | D9: Supervisor | E9: 876762396 | F9: DAO DUC HUY
A10: VA06 | B10: New Balance Crescent mall | C10: Chềnh Gia Hỷ | D10: Supervisor | E10: 366739361 | F10: VO LAM MINH DAT
A11: VA08 | B11: New Balance Diamond | C11: Nguyễn Hoàng Hiếu | D11: Supervisor | E11: 799411608 | F11: DUONG QUANG MINH TUAN
A12: VA01 | B12: New Balance Van Hanh Mall | C12: Tô Kim Hoàng | D12: Supervisor | E12: 903288823 | F12: DUONG QUANG MINH TUAN
... A29: VH02 | B29: Skechers Lotte Department | C29: Trần Đăng Khoa | D29: Supervisor | E29: 964960001 | F29: NGUYEN THI HONG NHUNG
A30: A001 | B30: Asics Lotte Mall | F30: NGUYEN THI HONG NHUNG
A31: VA19 | B31: New Balance Hanoi Center | F31: NGUYEN THI HONG NHUNG
A32: VO03 | B32: Foot Locker Hanoi Center | F32: NGUYEN THI HONG NHUNG
A33: VN28 | B33: Converse Hanoi Center | F33: NGUYEN THI HONG NHUNG
A34: VH01 | B34: Skechers Hanoi Center | F34: NGUYEN THI HONG NHUNG
A35: ZV32 | B35: Event Lotte Mall West Lake | C35: Nguyễn Thị Hồng Nhung | D35: AM | E35: 969230340 | F35: NGUYEN THI HONG NHUNG
